odoo/addons/website_adv_image_optimization/README.rst
odoo/addons/website_adv_image_optimization/__init__.py
odoo/addons/website_adv_image_optimization/__manifest__.py
odoo/addons/website_adv_image_optimization/controllers/__init__.py
odoo/addons/website_adv_image_optimization/controllers/main.py
odoo/addons/website_adv_image_optimization/static/description/screenshot0.png
odoo/addons/website_adv_image_optimization/static/src/css/website_adv_image_optimization.css
odoo/addons/website_adv_image_optimization/static/src/js/website_adv_image_optimization.js
odoo/addons/website_adv_image_optimization/static/src/xml/website_adv_image_optimization.xml
odoo/addons/website_adv_image_optimization/templates/assets.xml
odoo/addons/website_adv_image_optimization/tests/__init__.py
odoo/addons/website_adv_image_optimization/tests/test_controller.py
odoo11_addon_website_adv_image_optimization-11.0.1.0.0.dist-info/DESCRIPTION.rst
odoo11_addon_website_adv_image_optimization-11.0.1.0.0.dist-info/METADATA
odoo11_addon_website_adv_image_optimization-11.0.1.0.0.dist-info/RECORD
odoo11_addon_website_adv_image_optimization-11.0.1.0.0.dist-info/WHEEL
odoo11_addon_website_adv_image_optimization-11.0.1.0.0.dist-info/metadata.json
odoo11_addon_website_adv_image_optimization-11.0.1.0.0.dist-info/top_level.txt
